Metadata-Version: 2.4
Name: pyfuse3
Version: 3.4.2
Summary: Python 3 bindings for libfuse 3 with async I/O support
Author-email: Nikolaus Rath <Nikolaus@rath.org>
License-Expression: LGPL-2.1-or-later
Project-URL: Homepage, https://github.com/libfuse/pyfuse3
Keywords: FUSE,python
Classifier: Development Status :: 5 - Production/Stable
Classifier: Intended Audience :: Developers
Classifier: Programming Language :: Python
Classifier: Topic :: Software Development :: Libraries :: Python Modules
Classifier: Topic :: System :: Filesystems
Classifier: Operating System :: POSIX :: Linux
Classifier: Typing :: Typed
Requires-Python: >=3.10
License-File: LICENSE
Requires-Dist: trio>=0.15
Dynamic: license-file
